[{"Team":"Russia","Group":"A","Previous \nappearances":"10","Previous \ntitles":"0","Previous\n finals":"0","Previous\n semifinals":"1","Current \nFIFA rank":"65","First match \nagainst":"Saudi Arabia","Match index":"33","history with \nfirst opponent\n W-L":"-1","history with\n first opponent\n goals":"-2","Second match\n against":"Egypt","history with\n second opponent\n W-L":"N/A","history with\n second opponent\n goals":"N/A","Third match\n against":"Uruguay","history with\n third opponent\n W-L":"0","history with\n third opponent\n goals":"0","":""},
{"Team":"Saudi Arabia","Group":"A","Previous \nappearances":"4","Previous \ntitles":"0","Previous\n finals":"0","Previous\n semifinals":"0","Current \nFIFA rank":"63","First match \nagainst":"Russia","Match index":"34","history with \nfirst opponent\n W-L":"1","history with\n first opponent\n goals":"2","Second match\n against":"Uruguay","history with\n second opponent\n W-L":"1","history with\n second opponent\n goals":"1","Third match\n against":"Egypt","history with\n third opponent\n W-L":"-5","history with\n third opponent\n goals":"-5","":""},
{"Team":"Egypt","Group":"A","Previous \nappearances":"2","Previous \ntitles":"0","Previous\n finals":"0","Previous\n semifinals":"0","Current \nFIFA rank":"31","First match \nagainst":"Uruguay","Match index":"34","history with \nfirst opponent\n W-L":"-1","history with\n first opponent\n goals":"-2","Second match\n against":"Russia","history with\n second opponent\n W-L":"N/A","history with\n second opponent\n goals":"N/A","Third match\n against":"Saudi Arabia","history with\n third opponent\n W-L":"5","history with\n third opponent\n goals":"5","":""},
{"Team":"Uruguay","Group":"A","Previous \nappearances":"12","Previous \ntitles":"2","Previous\n finals":"2","Previous\n semifinals":"5","Current \nFIFA rank":"21","First match \nagainst":"Egypt","Match index":"33","history with \nfirst opponent\n W-L":"1","history with\n first opponent\n goals":"2","Second match\n against":"Saudi Arabia","history with\n second opponent\n W-L":"-1","history with\n second opponent\n goals":"-1","Third match\n against":"Russia","history with\n third opponent\n W-L":"0","history with\n third opponent\n goals":"0","":""},
{"Team":"Porugal","Group":"B","Previous \nappearances":"6","Previous \ntitles":"0","Previous\n finals":"0","Previous\n semifinals":"2","Current \nFIFA rank":"3","First match \nagainst":"Spain","Match index":"35","history with \nfirst opponent\n W-L":"-12","history with\n first opponent\n goals":"-31","Second match\n against":"Morocco","history with\n second opponent\n W-L":"-1","history with\n second opponent\n goals":"-2","Third match\n against":"Iran","history with\n third opponent\n W-L":"2","history with\n third opponent\n goals":"5","":""},
{"Team":"Spain","Group":"B","Previous \nappearances":"14","Previous \ntitles":"1","Previous\n finals":"1","Previous\n semifinals":"2","Current \nFIFA rank":"6","First match \nagainst":"Portugal","Match index":"36","history with \nfirst opponent\n W-L":"12","history with\n first opponent\n goals":"31","Second match\n against":"Iran","history with\n second opponent\n W-L":"N/A","history with\n second opponent\n goals":"N/A","Third match\n against":"Morocco","history with\n third opponent\n W-L":"5","history with\n third opponent\n goals":"7","":""},
{"Team":"Morocco","Group":"B","Previous \nappearances":"4","Previous \ntitles":"0","Previous\n finals":"0","Previous\n semifinals":"0","Current \nFIFA rank":"40","First match \nagainst":"Iran","Match index":"36","history with \nfirst opponent\n W-L":"-2","history with\n first opponent\n goals":"-2","Second match\n against":"Portugal","history with\n second opponent\n W-L":"1","history with\n second opponent\n goals":"2","Third match\n against":"Spain","history with\n third opponent\n W-L":"-5","history with\n third opponent\n goals":"-7","":""},
{"Team":"IRAN","Group":"B","Previous \nappearances":"4","Previous \ntitles":"0","Previous\n finals":"0","Previous\n semifinals":"0","Current \nFIFA rank":"32","First match \nagainst":"Morocco","Match index":"35","history with \nfirst opponent\n W-L":"2","history with\n first opponent\n goals":"2","Second match\n against":"Spain","history with\n second opponent\n W-L":"N/A","history with\n second opponent\n goals":"N/A","Third match\n against":"Portugal","history with\n third opponent\n W-L":"-2","history with\n third opponent\n goals":"-5","":""},
{"Team":"France","Group":"C","Previous \nappearances":"14","Previous \ntitles":"1","Previous\n finals":"2","Previous\n semifinals":"5","Current \nFIFA rank":"9","First match \nagainst":"Australia","Match index":"37","history with \nfirst opponent\n W-L":"1","history with\n first opponent\n goals":"6","Second match\n against":"Peru","history with\n second opponent\n W-L":"-1","history with\n second opponent\n goals":"-1","Third match\n against":"Denmark","history with\n third opponent\n W-L":"4","history with\n third opponent\n goals":"9","":""},
{"Team":"Australia","Group":"C","Previous \nappearances":"4","Previous \ntitles":"0","Previous\n finals":"0","Previous\n semifinals":"0","Current \nFIFA rank":"39","First match \nagainst":"France","Match index":"38","history with \nfirst opponent\n W-L":"-1","history with\n first opponent\n goals":"-6","Second match\n against":"Denmark","history with\n second opponent\n W-L":"-1","history with\n second opponent\n goals":"-3","Third match\n against":"Peru","history with\n third opponent\n W-L":"N/A","history with\n third opponent\n goals":"N/A","":""},
{"Team":"Peru","Group":"C","Previous \nappearances":"4","Previous \ntitles":"0","Previous\n finals":"0","Previous\n semifinals":"0","Current \nFIFA rank":"11","First match \nagainst":"Denmark","Match index":"38","history with \nfirst opponent\n W-L":"N/A","history with\n first opponent\n goals":"N/A","Second match\n against":"France","history with\n second opponent\n W-L":"1","history with\n second opponent\n goals":"1","Third match\n against":"Australia","history with\n third opponent\n W-L":"N/A","history with\n third opponent\n goals":"N/A","":""},
{"Team":"Denmark","Group":"C","Previous \nappearances":"4","Previous \ntitles":"0","Previous\n finals":"0","Previous\n semifinals":"0","Current \nFIFA rank":"12","First match \nagainst":"Peru","Match index":"37","history with \nfirst opponent\n W-L":"N/A","history with\n first opponent\n goals":"N/A","Second match\n against":"Australia","history with\n second opponent\n W-L":"1","history with\n second opponent\n goals":"3","Third match\n against":"France","history with\n third opponent\n W-L":"-4","history with\n third opponent\n goals":"-9","":""},
{"Team":"Argentina","Group":"D","Previous \nappearances":"16","Previous \ntitles":"2","Previous\n finals":"5","Previous\n semifinals":"5","Current \nFIFA rank":"4","First match \nagainst":"Iceland","Match index":"39","history with \nfirst opponent\n W-L":"N/A","history with\n first opponent\n goals":"N/A","Second match\n against":"Croatia","history with\n second opponent\n W-L":"1","history with\n second opponent\n goals":"0","Third match\n against":"Nigeria","history with\n third opponent\n W-L":"3","history with\n third opponent\n goals":"1","":""},
{"Team":"Iceland","Group":"D","Previous \nappearances":"0","Previous \ntitles":"0","Previous\n finals":"0","Previous\n semifinals":"0","Current \nFIFA rank":"22","First match \nagainst":"Argentina","Match index":"40","history with \nfirst opponent\n W-L":"N/A","history with\n first opponent\n goals":"N/A","Second match\n against":"Nigeria","history with\n second opponent\n W-L":"1","history with\n second opponent\n goals":"3","Third match\n against":"Croatia","history with\n third opponent\n W-L":"-3","history with\n third opponent\n goals":"-9","":""},
{"Team":"Croatia","Group":"D","Previous \nappearances":"4","Previous \ntitles":"0","Previous\n finals":"0","Previous\n semifinals":"1","Current \nFIFA rank":"17","First match \nagainst":"Nigeria","Match index":"40","history with \nfirst opponent\n W-L":"N/A","history with\n first opponent\n goals":"N/A","Second match\n against":"Argentina","history with\n second opponent\n W-L":"-1","history with\n second opponent\n goals":"0","Third match\n against":"Iceland","history with\n third opponent\n W-L":"3","history with\n third opponent\n goals":"9","":""},
{"Team":"Nigeria","Group":"D","Previous \nappearances":"5","Previous \ntitles":"0","Previous\n finals":"0","Previous\n semifinals":"0","Current \nFIFA rank":"50","First match \nagainst":"Croatia","Match index":"39","history with \nfirst opponent\n W-L":"N/A","history with\n first opponent\n goals":"N/A","Second match\n against":"Iceland","history with\n second opponent\n W-L":"-1","history with\n second opponent\n goals":"-3","Third match\n against":"Argentina","history with\n third opponent\n W-L":"-3","history with\n third opponent\n goals":"-1","":""},
{"Team":"Brazil","Group":"E","Previous \nappearances":"20","Previous \ntitles":"5","Previous\n finals":"7","Previous\n semifinals":"11","Current \nFIFA rank":"2","First match \nagainst":"Switzerland","Match index":"41","history with \nfirst opponent\n W-L":"1","history with\n first opponent\n goals":"2","Second match\n against":"Costarica","history with\n second opponent\n W-L":"8","history with\n second opponent\n goals":"19","Third match\n against":"Serbia","history with\n third opponent\n W-L":"1","history with\n third opponent\n goals":"1","":""},
{"Team":"Switzerland","Group":"E","Previous \nappearances":"10","Previous \ntitles":"0","Previous\n finals":"0","Previous\n semifinals":"0","Current \nFIFA rank":"8","First match \nagainst":"Brazil","Match index":"42","history with \nfirst opponent\n W-L":"-1","history with\n first opponent\n goals":"-2","Second match\n against":"Serbia","history with\n second opponent\n W-L":"N/A","history with\n second opponent\n goals":"N/A","Third match\n against":"Costarica","history with\n third opponent\n W-L":"0","history with\n third opponent\n goals":"1","":""},
{"Team":"Costarica","Group":"E","Previous \nappearances":"4","Previous \ntitles":"0","Previous\n finals":"0","Previous\n semifinals":"0","Current \nFIFA rank":"26","First match \nagainst":"Serbia","Match index":"42","history with \nfirst opponent\n W-L":"N/A","history with\n first opponent\n goals":"N/A","Second match\n against":"Brazil","history with\n second opponent\n W-L":"-8","history with\n second opponent\n goals":"-19","Third match\n against":"Switzerland","history with\n third opponent\n W-L":"0","history with\n third opponent\n goals":"-1","":""},
{"Team":"Serbia","Group":"E","Previous \nappearances":"11","Previous \ntitles":"0","Previous\n finals":"0","Previous\n semifinals":"2","Current \nFIFA rank":"37","First match \nagainst":"Costarica","Match index":"41","history with \nfirst opponent\n W-L":"N/A","history with\n first opponent\n goals":"N/A","Second match\n against":"Switzerland","history with\n second opponent\n W-L":"N/A","history with\n second opponent\n goals":"N/A","Third match\n against":"Brazil","history with\n third opponent\n W-L":"-1","history with\n third opponent\n goals":"-1","":""},
{"Team":"Germany","Group":"F","Previous \nappearances":"18","Previous \ntitles":"4","Previous\n finals":"8","Previous\n semifinals":"13","Current \nFIFA rank":"1","First match \nagainst":"Mexico","Match index":"43","history with \nfirst opponent\n W-L":"4","history with\n first opponent\n goals":"13","Second match\n against":"Sweden","history with\n second opponent\n W-L":"2","history with\n second opponent\n goals":"10","Third match\n against":"Korea","history with\n third opponent\n W-L":"1","history with\n third opponent\n goals":"0","":""},
{"Team":"Mexico","Group":"F","Previous \nappearances":"15","Previous \ntitles":"0","Previous\n finals":"0","Previous\n semifinals":"0","Current \nFIFA rank":"16","First match \nagainst":"Germany","Match index":"44","history with \nfirst opponent\n W-L":"-4","history with\n first opponent\n goals":"-13","Second match\n against":"Korea","history with\n second opponent\n W-L":"1","history with\n second opponent\n goals":"12","Third match\n against":"Sweden","history with\n third opponent\n W-L":"-2","history with\n third opponent\n goals":"-3","":""},
{"Team":"Sweden","Group":"F","Previous \nappearances":"11","Previous \ntitles":"0","Previous\n finals":"1","Previous\n semifinals":"4","Current \nFIFA rank":"18","First match \nagainst":"Korea","Match index":"44","history with \nfirst opponent\n W-L":"1","history with\n first opponent\n goals":"2","Second match\n against":"Germany","history with\n second opponent\n W-L":"-2","history with\n second opponent\n goals":"-10","Third match\n against":"Mexico","history with\n third opponent\n W-L":"2","history with\n third opponent\n goals":"3","":""},
{"Team":"Korea","Group":"F","Previous \nappearances":"9","Previous \ntitles":"0","Previous\n finals":"0","Previous\n semifinals":"1","Current \nFIFA rank":"59","First match \nagainst":"Sweden","Match index":"43","history with \nfirst opponent\n W-L":"-1","history with\n first opponent\n goals":"-2","Second match\n against":"Mexico","history with\n second opponent\n W-L":"-1","history with\n second opponent\n goals":"-10","Third match\n against":"Germany","history with\n third opponent\n W-L":"-1","history with\n third opponent\n goals":"0","":""},
{"Team":"Belgium","Group":"G","Previous \nappearances":"12","Previous \ntitles":"0","Previous\n finals":"0","Previous\n semifinals":"1","Current \nFIFA rank":"5","First match \nagainst":"Panama","Match index":"45","history with \nfirst opponent\n W-L":"N/A","history with\n first opponent\n goals":"N/A","Second match\n against":"Tunisia","history with\n second opponent\n W-L":"0","history with\n second opponent\n goals":"0","Third match\n against":"England","history with\n third opponent\n W-L":"-17","history with\n third opponent\n goals":"-70","":""},
{"Team":"Panama","Group":"G","Previous \nappearances":"0","Previous \ntitles":"0","Previous\n finals":"0","Previous\n semifinals":"0","Current \nFIFA rank":"56","First match \nagainst":"Belgium","Match index":"46","history with \nfirst opponent\n W-L":"N/A","history with\n first opponent\n goals":"N/A","Second match\n against":"England","history with\n second opponent\n W-L":"N/A","history with\n second opponent\n goals":"N/A","Third match\n against":"Tunisia","history with\n third opponent\n W-L":"N/A","history with\n third opponent\n goals":"N/A","":""},
{"Team":"Tunisia","Group":"G","Previous \nappearances":"4","Previous \ntitles":"0","Previous\n finals":"0","Previous\n semifinals":"0","Current \nFIFA rank":"27","First match \nagainst":"England","Match index":"46","history with \nfirst opponent\n W-L":"-1","history with\n first opponent\n goals":"-2","Second match\n against":"Belgium","history with\n second opponent\n W-L":"0","history with\n second opponent\n goals":"0","Third match\n against":"Panama","history with\n third opponent\n W-L":"N/A","history with\n third opponent\n goals":"N/A","":""},
{"Team":"England","Group":"G","Previous \nappearances":"14","Previous \ntitles":"1","Previous\n finals":"1","Previous\n semifinals":"2","Current \nFIFA rank":"15","First match \nagainst":"Tunisia","Match index":"45","history with \nfirst opponent\n W-L":"1","history with\n first opponent\n goals":"2","Second match\n against":"Panama","history with\n second opponent\n W-L":"N/A","history with\n second opponent\n goals":"N/A","Third match\n against":"Belgium","history with\n third opponent\n W-L":"17","history with\n third opponent\n goals":"70","":""},
{"Team":"Poland","Group":"H","Previous \nappearances":"7","Previous \ntitles":"0","Previous\n finals":"0","Previous\n semifinals":"2","Current \nFIFA rank":"7","First match \nagainst":"Senegal","Match index":"47","history with \nfirst opponent\n W-L":"N/A","history with\n first opponent\n goals":"N/A","Second match\n against":"Columbia","history with\n second opponent\n W-L":"N/A","history with\n second opponent\n goals":"N/A","Third match\n against":"Japan","history with\n third opponent\n W-L":"2","history with\n third opponent\n goals":"3","":""},
{"Team":"Senegal","Group":"H","Previous \nappearances":"1","Previous \ntitles":"0","Previous\n finals":"0","Previous\n semifinals":"0","Current \nFIFA rank":"23","First match \nagainst":"Poland","Match index":"48","history with \nfirst opponent\n W-L":"N/A","history with\n first opponent\n goals":"N/A","Second match\n against":"Japan","history with\n second opponent\n W-L":"2","history with\n second opponent\n goals":"3","Third match\n against":"Columbia","history with\n third opponent\n W-L":"0","history with\n third opponent\n goals":"0","":""},
{"Team":"Columbia","Group":"H","Previous \nappearances":"5","Previous \ntitles":"0","Previous\n finals":"0","Previous\n semifinals":"0","Current \nFIFA rank":"13","First match \nagainst":"Japan","Match index":"48","history with \nfirst opponent\n W-L":"2","history with\n first opponent\n goals":"2","Second match\n against":"Poland","history with\n second opponent\n W-L":"N/A","history with\n second opponent\n goals":"N/A","Third match\n against":"Senegal","history with\n third opponent\n W-L":"0","history with\n third opponent\n goals":"0","":""},
{"Team":"Japan","Group":"H","Previous \nappearances":"5","Previous \ntitles":"0","Previous\n finals":"0","Previous\n semifinals":"0","Current \nFIFA rank":"55","First match \nagainst":"Columbia","Match index":"47","history with \nfirst opponent\n W-L":"-2","history with\n first opponent\n goals":"-2","Second match\n against":"Senegal","history with\n second opponent\n W-L":"-2","history with\n second opponent\n goals":"-3","Third match\n against":"Poland","history with\n third opponent\n W-L":"-2","history with\n third opponent\n goals":"-3","":""},
{"Team":"","Group":"","Previous \nappearances":"","Previous \ntitles":"","Previous\n finals":"","Previous\n semifinals":"","Current \nFIFA rank":"","First match \nagainst":"","Match index":"","history with \nfirst opponent\n W-L":"","history with\n first opponent\n goals":"","Second match\n against":"","history with\n second opponent\n W-L":"","history with\n second opponent\n goals":"","Third match\n against":"","history with\n third opponent\n W-L":"","history with\n third opponent\n goals":"","":""},
{"Team":""}]
